{"Version":"1.0.0.0","LastState":11,"Modules":[{"ModuleName":"Front Left","ModuleId":0,"Encoder":{"Id":11,"Name":"CANCoder FL (11)","Model":"CANCoder","CANbus":"rio","CANbusFriendly":"","SelectedMotorType":null,"IsStandaloneFx":false},"SteerMotor":{"Id":1,"Name":"FL Turn (1)","Model":"Talon FX vers. C","CANbus":"rio","CANbusFriendly":"","SelectedMotorType":{"Name":"WCP Kraken x60","FreeSpeedRps":96.7},"IsStandaloneFx":false},"DriveMotor":{"Id":2,"Name":"FL Drive (2)","Model":"Talon FX vers. C","CANbus":"rio","CANbusFriendly":"","SelectedMotorType":{"Name":"WCP Kraken x60","FreeSpeedRps":96.7},"IsStandaloneFx":false},"IsEncoderInverted":true,"IsSteerInverted":false,"SelectedEncoderType":"CANcoder","EncoderOffset":-0.24658203125,"DriveMotorSelectionState":1,"SteerMotorSelectionState":1,"SteerEncoderSelectionState":1,"IsModuleValidationComplete":true,"ValidatedSteerId":1,"ValidatedDriveId":2,"ValidatedEncoderId":11,"AvailEncoders":[],"IsEncoderTypeCAN":true,"IsDeviceSelectionCompleted":true,"IsConfigurationCompleted":true,"AvailEncoderTypes":["CANcoder"]},{"ModuleName":"Front Right","ModuleId":1,"Encoder":{"Id":12,"Name":"CANCoder FR (12)","Model":"CANCoder","CANbus":"rio","CANbusFriendly":"","SelectedMotorType":null,"IsStandaloneFx":false},"SteerMotor":{"Id":3,"Name":"FR Turn (3)","Model":"Talon FX vers. C","CANbus":"rio","CANbusFriendly":"","SelectedMotorType":{"Name":"WCP Kraken x60","FreeSpeedRps":96.7},"IsStandaloneFx":false},"DriveMotor":{"Id":4,"Name":"FR Drive  (4)","Model":"Talon FX vers. C","CANbus":"rio","CANbusFriendly":"","SelectedMotorType":{"Name":"WCP Kraken x60","FreeSpeedRps":96.7},"IsStandaloneFx":false},"IsEncoderInverted":true,"IsSteerInverted":false,"SelectedEncoderType":"CANcoder","EncoderOffset":0.200439453125,"DriveMotorSelectionState":1,"SteerMotorSelectionState":1,"SteerEncoderSelectionState":1,"IsModuleValidationComplete":true,"ValidatedSteerId":3,"ValidatedDriveId":4,"ValidatedEncoderId":12,"AvailEncoders":[],"IsEncoderTypeCAN":true,"IsDeviceSelectionCompleted":true,"IsConfigurationCompleted":true,"AvailEncoderTypes":["CANcoder"]},{"ModuleName":"Back Left","ModuleId":2,"Encoder":{"Id":13,"Name":"CANCoder BL (13)","Model":"CANCoder","CANbus":"rio","CANbusFriendly":"","SelectedMotorType":null,"IsStandaloneFx":false},"SteerMotor":{"Id":7,"Name":"BL Turn (7)","Model":"Talon FX vers. C","CANbus":"rio","CANbusFriendly":"","SelectedMotorType":{"Name":"WCP Kraken x60","FreeSpeedRps":96.7},"IsStandaloneFx":false},"DriveMotor":{"Id":8,"Name":"BL Drive (8)","Model":"Talon FX vers. C","CANbus":"rio","CANbusFriendly":"","SelectedMotorType":{"Name":"WCP Kraken x60","FreeSpeedRps":96.7},"IsStandaloneFx":false},"IsEncoderInverted":true,"IsSteerInverted":false,"SelectedEncoderType":"CANcoder","EncoderOffset":0.332275390625,"DriveMotorSelectionState":1,"SteerMotorSelectionState":1,"SteerEncoderSelectionState":1,"IsModuleValidationComplete":true,"ValidatedSteerId":7,"ValidatedDriveId":8,"ValidatedEncoderId":13,"AvailEncoders":[],"IsEncoderTypeCAN":true,"IsDeviceSelectionCompleted":true,"IsConfigurationCompleted":true,"AvailEncoderTypes":["CANcoder"]},{"ModuleName":"Back Right","ModuleId":3,"Encoder":{"Id":14,"Name":"CANCoder BR (14)","Model":"CANCoder","CANbus":"rio","CANbusFriendly":"","SelectedMotorType":null,"IsStandaloneFx":false},"SteerMotor":{"Id":5,"Name":"BR Turn (5)","Model":"Talon FX vers. C","CANbus":"rio","CANbusFriendly":"","SelectedMotorType":{"Name":"WCP Kraken x60","FreeSpeedRps":96.7},"IsStandaloneFx":false},"DriveMotor":{"Id":6,"Name":"BR Drive (6)","Model":"Talon FX vers. C","CANbus":"rio","CANbusFriendly":"","SelectedMotorType":{"Name":"WCP Kraken x60","FreeSpeedRps":96.7},"IsStandaloneFx":false},"IsEncoderInverted":true,"IsSteerInverted":false,"SelectedEncoderType":"CANcoder","EncoderOffset":-0.32763671875,"DriveMotorSelectionState":1,"SteerMotorSelectionState":1,"SteerEncoderSelectionState":1,"IsModuleValidationComplete":true,"ValidatedSteerId":5,"ValidatedDriveId":6,"ValidatedEncoderId":14,"AvailEncoders":[],"IsEncoderTypeCAN":true,"IsDeviceSelectionCompleted":true,"IsConfigurationCompleted":true,"AvailEncoderTypes":["CANcoder"]}],"SwerveOptions":{"kSpeedAt12Volts":"Infinity","Gyro":{"Id":15,"Name":"Pigeon 2 vers. S (15)","Model":"Pigeon 2 vers. S","CANbus":"rio","CANbusFriendly":"","SelectedMotorType":null,"IsStandaloneFx":false},"IsValidGyroCANbus":true,"VerticalTrackSizeInches":24.5,"HorizontalTrackSizeInches":24.5,"WheelRadiusInches":2.0,"IsLeftSideInverted":true,"IsRightSideInverted":false,"SwerveModuleType":8,"SwerveModuleConfiguration":{"ModuleBrand":-1,"DriveRatio":0.0,"SteerRatio":0.0,"CouplingRatio":0.0,"CustomName":null},"HasVerifiedSteer":true,"HasVerifiedDrive":true,"IsValidConfiguration":false}}